[
  {
    "id": 1,
    "location": "123 Main Street, Chintal, Cherkupally colony hyderabad",
    "type": "Sale",
    "price": "5,00,000",
    "agent": "Srikanth Real Estates",
    "bedrooms": 3,
    "bathrooms": 2,
    "sqfoot": 1200,
    "postedOn": "5 days ago",
    "images": [
      "https://images.pexels.com/photos/1029599/pexels-photo-1029599.jpeg?auto=compress&cs=tinysrgb&w=1260&h=750&dpr=1",
      "https://images.pexels.com/photos/1974596/pexels-photo-1974596.jpeg?auto=compress&cs=tinysrgb&w=1260&h=750&dpr=1",
      "https://images.pexels.com/photos/3965528/pexels-photo-3965528.jpeg?auto=compress&cs=tinysrgb&w=1260&h=750&dpr=1",
      "https://images.pexels.com/photos/2102587/pexels-photo-2102587.jpeg?auto=compress&cs=tinysrgb&w=1260&h=750&dpr=1",
      "https://images.pexels.com/photos/1396122/pexels-photo-1396122.jpeg?auto=compress&cs=tinysrgb&w=1260&h=750&dpr=1",
      "https://images.pexels.com/photos/259588/pexels-photo-259588.jpeg?auto=compress&cs=tinysrgb&w=1260&h=750&dpr=1",
      "https://images.pexels.com/photos/164558/pexels-photo-164558.jpeg?auto=compress&cs=tinysrgb&w=1260&h=750&dpr=1",
      "https://images.pexels.com/photos/2635038/pexels-photo-2635038.jpeg?auto=compress&cs=tinysrgb&w=1260&h=750&dpr=1",
      "https://images.pexels.com/photos/1438832/pexels-photo-1438832.jpeg?auto=compress&cs=tinysrgb&w=1260&h=750&dpr=1"
    ]
  },
  {
    "id": 2,
    "location": "123 Main Street, Chintal, Cherkupally colony hyderabad",
    "type": "Sale",
    "price": "5,10,000",
    "agent": "Srikanth Real Estates",
    "bedrooms": 3,
    "bathrooms": 2,
    "sqfoot": 1200,
    "postedOn": "5 days ago",
    "images": [
      "https://images.pexels.com/photos/1029599/pexels-photo-1029599.jpeg?auto=compress&cs=tinysrgb&w=1260&h=750&dpr=1",
      "https://images.pexels.com/photos/1974596/pexels-photo-1974596.jpeg?auto=compress&cs=tinysrgb&w=1260&h=750&dpr=1",
      "https://images.pexels.com/photos/3965528/pexels-photo-3965528.jpeg?auto=compress&cs=tinysrgb&w=1260&h=750&dpr=1",
      "https://images.pexels.com/photos/2102587/pexels-photo-2102587.jpeg?auto=compress&cs=tinysrgb&w=1260&h=750&dpr=1",
      "https://images.pexels.com/photos/1396122/pexels-photo-1396122.jpeg?auto=compress&cs=tinysrgb&w=1260&h=750&dpr=1",
      "https://images.pexels.com/photos/259588/pexels-photo-259588.jpeg?auto=compress&cs=tinysrgb&w=1260&h=750&dpr=1",
      "https://images.pexels.com/photos/164558/pexels-photo-164558.jpeg?auto=compress&cs=tinysrgb&w=1260&h=750&dpr=1",
      "https://images.pexels.com/photos/2635038/pexels-photo-2635038.jpeg?auto=compress&cs=tinysrgb&w=1260&h=750&dpr=1",
      "https://images.pexels.com/photos/1438832/pexels-photo-1438832.jpeg?auto=compress&cs=tinysrgb&w=1260&h=750&dpr=1"
    ]
  },
  {
    "id": 3,
    "location": "123 Main Street, Chintal, Cherkupally colony hyderabad",
    "type": "Sale",
    "price": "5,20,000",
    "agent": "Srikanth Real Estates",
    "bedrooms": 3,
    "bathrooms": 2,
    "sqfoot": 1200,
    "postedOn": "5 days ago",
    "images": [
      "https://images.pexels.com/photos/1029599/pexels-photo-1029599.jpeg?auto=compress&cs=tinysrgb&w=1260&h=750&dpr=1",
      "https://images.pexels.com/photos/1974596/pexels-photo-1974596.jpeg?auto=compress&cs=tinysrgb&w=1260&h=750&dpr=1",
      "https://images.pexels.com/photos/3965528/pexels-photo-3965528.jpeg?auto=compress&cs=tinysrgb&w=1260&h=750&dpr=1",
      "https://images.pexels.com/photos/2102587/pexels-photo-2102587.jpeg?auto=compress&cs=tinysrgb&w=1260&h=750&dpr=1",
      "https://images.pexels.com/photos/1396122/pexels-photo-1396122.jpeg?auto=compress&cs=tinysrgb&w=1260&h=750&dpr=1",
      "https://images.pexels.com/photos/259588/pexels-photo-259588.jpeg?auto=compress&cs=tinysrgb&w=1260&h=750&dpr=1",
      "https://images.pexels.com/photos/164558/pexels-photo-164558.jpeg?auto=compress&cs=tinysrgb&w=1260&h=750&dpr=1",
      "https://images.pexels.com/photos/2635038/pexels-photo-2635038.jpeg?auto=compress&cs=tinysrgb&w=1260&h=750&dpr=1",
      "https://images.pexels.com/photos/1438832/pexels-photo-1438832.jpeg?auto=compress&cs=tinysrgb&w=1260&h=750&dpr=1"
    ]
  },
  {
    "id": 4,
    "location": "123 Main Street, Chintal, Cherkupally colony hyderabad",
    "type": "Sale",
    "price": "5,50,000",
    "agent": "Srikanth Real Estates",
    "bedrooms": 3,
    "bathrooms": 2,
    "sqfoot": 1200,
    "postedOn": "5 days ago",
    "images": [
      "https://images.pexels.com/photos/1029599/pexels-photo-1029599.jpeg?auto=compress&cs=tinysrgb&w=1260&h=750&dpr=1",
      "https://images.pexels.com/photos/1974596/pexels-photo-1974596.jpeg?auto=compress&cs=tinysrgb&w=1260&h=750&dpr=1",
      "https://images.pexels.com/photos/3965528/pexels-photo-3965528.jpeg?auto=compress&cs=tinysrgb&w=1260&h=750&dpr=1",
      "https://images.pexels.com/photos/2102587/pexels-photo-2102587.jpeg?auto=compress&cs=tinysrgb&w=1260&h=750&dpr=1",
      "https://images.pexels.com/photos/1396122/pexels-photo-1396122.jpeg?auto=compress&cs=tinysrgb&w=1260&h=750&dpr=1",
      "https://images.pexels.com/photos/259588/pexels-photo-259588.jpeg?auto=compress&cs=tinysrgb&w=1260&h=750&dpr=1",
      "https://images.pexels.com/photos/164558/pexels-photo-164558.jpeg?auto=compress&cs=tinysrgb&w=1260&h=750&dpr=1",
      "https://images.pexels.com/photos/2635038/pexels-photo-2635038.jpeg?auto=compress&cs=tinysrgb&w=1260&h=750&dpr=1",
      "https://images.pexels.com/photos/1438832/pexels-photo-1438832.jpeg?auto=compress&cs=tinysrgb&w=1260&h=750&dpr=1"
    ]
  }
]
